[
    {
        "ano": 2000,
        "populacao_total": 7601788,
        "homens": 3747816,
        "mulheres": 3853972,
        "nascimentos": 180124,
        "obitos": 53469,
        "taxa_crescimento_geometrico": null,
        "taxa_bruta_natalidade": 23.69,
        "taxa_bruga_mortalidade": 7.03,
        "esperanca_vida_nascer": 69.44,
        "esperanca_vida_nascer_homens": 65.75,
        "esperanca_vida_nascer_mulheres": 73.29,
        "taxa_mortalidade_infantil": 38.09,
        "taxa_mortalidade_infantil_homens": 44.66,
        "taxa_mortalidade_infantil_mulheres": 31.19,
        "taxa_fecundidade": 2.84,
        "razao_dependencia_jovens": 56.71,
        "razao_dependencia_idosos": 9.78,
        "razao_dependencia": 66.49,
        "indice_envelhecimento": 17.25
    },
    {
        "ano": 2001,
        "populacao_total": 7718435,
        "homens": 3804983,
        "mulheres": 3913452,
        "nascimentos": 176530,
        "obitos": 53413,
        "taxa_crescimento_geometrico": 1.53,
        "taxa_bruta_natalidade": 22.87,
        "taxa_bruga_mortalidade": 6.92,
        "esperanca_vida_nascer": 69.76,
        "esperanca_vida_nascer_homens": 66.05,
        "esperanca_vida_nascer_mulheres": 73.64,
        "taxa_mortalidade_infantil": 35.56,
        "taxa_mortalidade_infantil_homens": 41.37,
        "taxa_mortalidade_infantil_mulheres": 29.45,
        "taxa_fecundidade": 2.72,
        "razao_dependencia_jovens": 55.18,
        "razao_dependencia_idosos": 9.72,
        "razao_dependencia": 64.91,
        "indice_envelhecimento": 17.62
    },
    {
        "ano": 2002,
        "populacao_total": 7830721,
        "homens": 3859773,
        "mulheres": 3970948,
        "nascimentos": 172989,
        "obitos": 53198,
        "taxa_crescimento_geometrico": 1.45,
        "taxa_bruta_natalidade": 22.09,
        "taxa_bruga_mortalidade": 6.79,
        "esperanca_vida_nascer": 70.08,
        "esperanca_vida_nascer_homens": 66.34,
        "esperanca_vida_nascer_mulheres": 73.99,
        "taxa_mortalidade_infantil": 33.2,
        "taxa_mortalidade_infantil_homens": 38.33,
        "taxa_mortalidade_infantil_mulheres": 27.79,
        "taxa_fecundidade": 2.61,
        "razao_dependencia_jovens": 53.67,
        "razao_dependencia_idosos": 9.72,
        "razao_dependencia": 63.39,
        "indice_envelhecimento": 18.11
    },
    {
        "ano": 2003,
        "populacao_total": 7938714,
        "homens": 3912214,
        "mulheres": 4026500,
        "nascimentos": 169489,
        "obitos": 53060,
        "taxa_crescimento_geometrico": 1.38,
        "taxa_bruta_natalidade": 21.35,
        "taxa_bruga_mortalidade": 6.68,
        "esperanca_vida_nascer": 70.4,
        "esperanca_vida_nascer_homens": 66.63,
        "esperanca_vida_nascer_mulheres": 74.32,
        "taxa_mortalidade_infantil": 30.99,
        "taxa_mortalidade_infantil_homens": 35.53,
        "taxa_mortalidade_infantil_mulheres": 26.21,
        "taxa_fecundidade": 2.5,
        "razao_dependencia_jovens": 52.2,
        "razao_dependencia_idosos": 9.75,
        "razao_dependencia": 61.95,
        "indice_envelhecimento": 18.69
    },
    {
        "ano": 2004,
        "populacao_total": 8042368,
        "homens": 3962287,
        "mulheres": 4080081,
        "nascimentos": 166003,
        "obitos": 52997,
        "taxa_crescimento_geometrico": 1.31,
        "taxa_bruta_natalidade": 20.64,
        "taxa_bruga_mortalidade": 6.59,
        "esperanca_vida_nascer": 70.7,
        "esperanca_vida_nascer_homens": 66.91,
        "esperanca_vida_nascer_mulheres": 74.64,
        "taxa_mortalidade_infantil": 28.94,
        "taxa_mortalidade_infantil_homens": 32.96,
        "taxa_mortalidade_infantil_mulheres": 24.72,
        "taxa_fecundidade": 2.4,
        "razao_dependencia_jovens": 50.77,
        "razao_dependencia_idosos": 9.79,
        "razao_dependencia": 60.56,
        "indice_envelhecimento": 19.29
    },
    {
        "ano": 2005,
        "populacao_total": 8141584,
        "homens": 4009929,
        "mulheres": 4131655,
        "nascimentos": 162535,
        "obitos": 53027,
        "taxa_crescimento_geometrico": 1.23,
        "taxa_bruta_natalidade": 19.96,
        "taxa_bruga_mortalidade": 6.51,
        "esperanca_vida_nascer": 71.0,
        "esperanca_vida_nascer_homens": 67.18,
        "esperanca_vida_nascer_mulheres": 74.96,
        "taxa_mortalidade_infantil": 27.06,
        "taxa_mortalidade_infantil_homens": 30.6,
        "taxa_mortalidade_infantil_mulheres": 23.32,
        "taxa_fecundidade": 2.31,
        "razao_dependencia_jovens": 49.38,
        "razao_dependencia_idosos": 9.82,
        "razao_dependencia": 59.2,
        "indice_envelhecimento": 19.9
    },
    {
        "ano": 2006,
        "populacao_total": 8236289,
        "homens": 4055104,
        "mulheres": 4181185,
        "nascimentos": 159153,
        "obitos": 53152,
        "taxa_crescimento_geometrico": 1.16,
        "taxa_bruta_natalidade": 19.32,
        "taxa_bruga_mortalidade": 6.45,
        "esperanca_vida_nascer": 71.29,
        "esperanca_vida_nascer_homens": 67.45,
        "esperanca_vida_nascer_mulheres": 75.26,
        "taxa_mortalidade_infantil": 25.31,
        "taxa_mortalidade_infantil_homens": 28.46,
        "taxa_mortalidade_infantil_mulheres": 22.0,
        "taxa_fecundidade": 2.23,
        "razao_dependencia_jovens": 48.03,
        "razao_dependencia_idosos": 9.85,
        "razao_dependencia": 57.89,
        "indice_envelhecimento": 20.52
    },
    {
        "ano": 2007,
        "populacao_total": 8326445,
        "homens": 4097799,
        "mulheres": 4228646,
        "nascimentos": 155907,
        "obitos": 53394,
        "taxa_crescimento_geometrico": 1.09,
        "taxa_bruta_natalidade": 18.72,
        "taxa_bruga_mortalidade": 6.41,
        "esperanca_vida_nascer": 71.58,
        "esperanca_vida_nascer_homens": 67.72,
        "esperanca_vida_nascer_mulheres": 75.56,
        "taxa_mortalidade_infantil": 23.71,
        "taxa_mortalidade_infantil_homens": 26.5,
        "taxa_mortalidade_infantil_mulheres": 20.77,
        "taxa_fecundidade": 2.15,
        "razao_dependencia_jovens": 46.73,
        "razao_dependencia_idosos": 9.88,
        "razao_dependencia": 56.61,
        "indice_envelhecimento": 21.15
    },
    {
        "ano": 2008,
        "populacao_total": 8412055,
        "homens": 4138013,
        "mulheres": 4274042,
        "nascimentos": 152801,
        "obitos": 53716,
        "taxa_crescimento_geometrico": 1.03,
        "taxa_bruta_natalidade": 18.16,
        "taxa_bruga_mortalidade": 6.39,
        "esperanca_vida_nascer": 71.86,
        "esperanca_vida_nascer_homens": 67.98,
        "esperanca_vida_nascer_mulheres": 75.85,
        "taxa_mortalidade_infantil": 22.24,
        "taxa_mortalidade_infantil_homens": 24.73,
        "taxa_mortalidade_infantil_mulheres": 19.63,
        "taxa_fecundidade": 2.08,
        "razao_dependencia_jovens": 45.47,
        "razao_dependencia_idosos": 9.92,
        "razao_dependencia": 55.39,
        "indice_envelhecimento": 21.82
    },
    {
        "ano": 2009,
        "populacao_total": 8493155,
        "homens": 4175751,
        "mulheres": 4317404,
        "nascimentos": 149832,
        "obitos": 54094,
        "taxa_crescimento_geometrico": 0.96,
        "taxa_bruta_natalidade": 17.64,
        "taxa_bruga_mortalidade": 6.37,
        "esperanca_vida_nascer": 72.14,
        "esperanca_vida_nascer_homens": 68.24,
        "esperanca_vida_nascer_mulheres": 76.13,
        "taxa_mortalidade_infantil": 20.9,
        "taxa_mortalidade_infantil_homens": 23.12,
        "taxa_mortalidade_infantil_mulheres": 18.57,
        "taxa_fecundidade": 2.02,
        "razao_dependencia_jovens": 44.26,
        "razao_dependencia_idosos": 9.99,
        "razao_dependencia": 54.25,
        "indice_envelhecimento": 22.57
    },
    {
        "ano": 2010,
        "populacao_total": 8569783,
        "homens": 4211036,
        "mulheres": 4358747,
        "nascimentos": 146995,
        "obitos": 54523,
        "taxa_crescimento_geometrico": 0.9,
        "taxa_bruta_natalidade": 17.15,
        "taxa_bruga_mortalidade": 6.36,
        "esperanca_vida_nascer": 72.4,
        "esperanca_vida_nascer_homens": 68.49,
        "esperanca_vida_nascer_mulheres": 76.4,
        "taxa_mortalidade_infantil": 19.68,
        "taxa_mortalidade_infantil_homens": 21.67,
        "taxa_mortalidade_infantil_mulheres": 17.59,
        "taxa_fecundidade": 1.96,
        "razao_dependencia_jovens": 43.1,
        "razao_dependencia_idosos": 10.1,
        "razao_dependencia": 53.2,
        "indice_envelhecimento": 23.43
    },
    {
        "ano": 2011,
        "populacao_total": 8642630,
        "homens": 4244294,
        "mulheres": 4398336,
        "nascimentos": 144318,
        "obitos": 55023,
        "taxa_crescimento_geometrico": 0.85,
        "taxa_bruta_natalidade": 16.7,
        "taxa_bruga_mortalidade": 6.37,
        "esperanca_vida_nascer": 72.65,
        "esperanca_vida_nascer_homens": 68.74,
        "esperanca_vida_nascer_mulheres": 76.66,
        "taxa_mortalidade_infantil": 18.57,
        "taxa_mortalidade_infantil_homens": 20.36,
        "taxa_mortalidade_infantil_mulheres": 16.68,
        "taxa_fecundidade": 1.91,
        "razao_dependencia_jovens": 41.97,
        "razao_dependencia_idosos": 10.24,
        "razao_dependencia": 52.21,
        "indice_envelhecimento": 24.4
    },
    {
        "ano": 2012,
        "populacao_total": 8712413,
        "homens": 4275986,
        "mulheres": 4436427,
        "nascimentos": 141830,
        "obitos": 55563,
        "taxa_crescimento_geometrico": 0.81,
        "taxa_bruta_natalidade": 16.28,
        "taxa_bruga_mortalidade": 6.38,
        "esperanca_vida_nascer": 72.91,
        "esperanca_vida_nascer_homens": 68.98,
        "esperanca_vida_nascer_mulheres": 76.91,
        "taxa_mortalidade_infantil": 17.56,
        "taxa_mortalidade_infantil_homens": 19.18,
        "taxa_mortalidade_infantil_mulheres": 15.86,
        "taxa_fecundidade": 1.87,
        "razao_dependencia_jovens": 40.86,
        "razao_dependencia_idosos": 10.41,
        "razao_dependencia": 51.28,
        "indice_envelhecimento": 25.48
    },
    {
        "ano": 2013,
        "populacao_total": 8779338,
        "homens": 4306216,
        "mulheres": 4473122,
        "nascimentos": 139533,
        "obitos": 56137,
        "taxa_crescimento_geometrico": 0.77,
        "taxa_bruta_natalidade": 15.89,
        "taxa_bruga_mortalidade": 6.39,
        "esperanca_vida_nascer": 73.15,
        "esperanca_vida_nascer_homens": 69.22,
        "esperanca_vida_nascer_mulheres": 77.16,
        "taxa_mortalidade_infantil": 16.65,
        "taxa_mortalidade_infantil_homens": 18.12,
        "taxa_mortalidade_infantil_mulheres": 15.1,
        "taxa_fecundidade": 1.82,
        "razao_dependencia_jovens": 39.77,
        "razao_dependencia_idosos": 10.6,
        "razao_dependencia": 50.37,
        "indice_envelhecimento": 26.66
    },
    {
        "ano": 2014,
        "populacao_total": 8843553,
        "homens": 4335073,
        "mulheres": 4508480,
        "nascimentos": 137421,
        "obitos": 56754,
        "taxa_crescimento_geometrico": 0.73,
        "taxa_bruta_natalidade": 15.54,
        "taxa_bruga_mortalidade": 6.42,
        "esperanca_vida_nascer": 73.39,
        "esperanca_vida_nascer_homens": 69.46,
        "esperanca_vida_nascer_mulheres": 77.39,
        "taxa_mortalidade_infantil": 15.81,
        "taxa_mortalidade_infantil_homens": 17.16,
        "taxa_mortalidade_infantil_mulheres": 14.4,
        "taxa_fecundidade": 1.79,
        "razao_dependencia_jovens": 38.67,
        "razao_dependencia_idosos": 10.8,
        "razao_dependencia": 49.48,
        "indice_envelhecimento": 27.94
    },
    {
        "ano": 2015,
        "populacao_total": 8905225,
        "homens": 4362647,
        "mulheres": 4542578,
        "nascimentos": 135485,
        "obitos": 57372,
        "taxa_crescimento_geometrico": 0.7,
        "taxa_bruta_natalidade": 15.21,
        "taxa_bruga_mortalidade": 6.44,
        "esperanca_vida_nascer": 73.62,
        "esperanca_vida_nascer_homens": 69.69,
        "esperanca_vida_nascer_mulheres": 77.62,
        "taxa_mortalidade_infantil": 15.07,
        "taxa_mortalidade_infantil_homens": 16.3,
        "taxa_mortalidade_infantil_mulheres": 13.77,
        "taxa_fecundidade": 1.76,
        "razao_dependencia_jovens": 37.58,
        "razao_dependencia_idosos": 11.01,
        "razao_dependencia": 48.58,
        "indice_envelhecimento": 29.29
    },
    {
        "ano": 2016,
        "populacao_total": 8964432,
        "homens": 4388969,
        "mulheres": 4575463,
        "nascimentos": 133513,
        "obitos": 58024,
        "taxa_crescimento_geometrico": 0.66,
        "taxa_bruta_natalidade": 14.89,
        "taxa_bruga_mortalidade": 6.47,
        "esperanca_vida_nascer": 73.85,
        "esperanca_vida_nascer_homens": 69.91,
        "esperanca_vida_nascer_mulheres": 77.85,
        "taxa_mortalidade_infantil": 14.4,
        "taxa_mortalidade_infantil_homens": 15.54,
        "taxa_mortalidade_infantil_mulheres": 13.2,
        "taxa_fecundidade": 1.73,
        "razao_dependencia_jovens": 36.47,
        "razao_dependencia_idosos": 11.21,
        "razao_dependencia": 47.68,
        "indice_envelhecimento": 30.74
    },
    {
        "ano": 2017,
        "populacao_total": 9021232,
        "homens": 4414082,
        "mulheres": 4607150,
        "nascimentos": 131706,
        "obitos": 58721,
        "taxa_crescimento_geometrico": 0.63,
        "taxa_bruta_natalidade": 14.6,
        "taxa_bruga_mortalidade": 6.51,
        "esperanca_vida_nascer": 74.07,
        "esperanca_vida_nascer_homens": 70.13,
        "esperanca_vida_nascer_mulheres": 78.06,
        "taxa_mortalidade_infantil": 13.79,
        "taxa_mortalidade_infantil_homens": 14.85,
        "taxa_mortalidade_infantil_mulheres": 12.67,
        "taxa_fecundidade": 1.7,
        "razao_dependencia_jovens": 35.44,
        "razao_dependencia_idosos": 11.43,
        "razao_dependencia": 46.87,
        "indice_envelhecimento": 32.25
    },
    {
        "ano": 2018,
        "populacao_total": 9075744,
        "homens": 4438062,
        "mulheres": 4637682,
        "nascimentos": 130042,
        "obitos": 59460,
        "taxa_crescimento_geometrico": 0.6,
        "taxa_bruta_natalidade": 14.33,
        "taxa_bruga_mortalidade": 6.55,
        "esperanca_vida_nascer": 74.28,
        "esperanca_vida_nascer_homens": 70.34,
        "esperanca_vida_nascer_mulheres": 78.26,
        "taxa_mortalidade_infantil": 13.24,
        "taxa_mortalidade_infantil_homens": 14.23,
        "taxa_mortalidade_infantil_mulheres": 12.2,
        "taxa_fecundidade": 1.68,
        "razao_dependencia_jovens": 34.48,
        "razao_dependencia_idosos": 11.66,
        "razao_dependencia": 46.14,
        "indice_envelhecimento": 33.82
    },
    {
        "ano": 2019,
        "populacao_total": 9128090,
        "homens": 4460962,
        "mulheres": 4667128,
        "nascimentos": 128501,
        "obitos": 60224,
        "taxa_crescimento_geometrico": 0.58,
        "taxa_bruta_natalidade": 14.08,
        "taxa_bruga_mortalidade": 6.6,
        "esperanca_vida_nascer": 74.48,
        "esperanca_vida_nascer_homens": 70.55,
        "esperanca_vida_nascer_mulheres": 78.46,
        "taxa_mortalidade_infantil": 12.75,
        "taxa_mortalidade_infantil_homens": 13.68,
        "taxa_mortalidade_infantil_mulheres": 11.77,
        "taxa_fecundidade": 1.66,
        "razao_dependencia_jovens": 33.58,
        "razao_dependencia_idosos": 11.91,
        "razao_dependencia": 45.49,
        "indice_envelhecimento": 35.46
    },
    {
        "ano": 2020,
        "populacao_total": 9178363,
        "homens": 4482835,
        "mulheres": 4695528,
        "nascimentos": 127055,
        "obitos": 61029,
        "taxa_crescimento_geometrico": 0.55,
        "taxa_bruta_natalidade": 13.84,
        "taxa_bruga_mortalidade": 6.65,
        "esperanca_vida_nascer": 74.68,
        "esperanca_vida_nascer_homens": 70.75,
        "esperanca_vida_nascer_mulheres": 78.65,
        "taxa_mortalidade_infantil": 12.31,
        "taxa_mortalidade_infantil_homens": 13.19,
        "taxa_mortalidade_infantil_mulheres": 11.38,
        "taxa_fecundidade": 1.64,
        "razao_dependencia_jovens": 32.75,
        "razao_dependencia_idosos": 12.17,
        "razao_dependencia": 44.91,
        "indice_envelhecimento": 37.16
    },
    {
        "ano": 2021,
        "populacao_total": 9226629,
        "homens": 4503719,
        "mulheres": 4722910,
        "nascimentos": 125676,
        "obitos": 61859,
        "taxa_crescimento_geometrico": 0.53,
        "taxa_bruta_natalidade": 13.62,
        "taxa_bruga_mortalidade": 6.7,
        "esperanca_vida_nascer": 74.88,
        "esperanca_vida_nascer_homens": 70.95,
        "esperanca_vida_nascer_mulheres": 78.84,
        "taxa_mortalidade_infantil": 11.91,
        "taxa_mortalidade_infantil_homens": 12.75,
        "taxa_mortalidade_infantil_mulheres": 11.03,
        "taxa_fecundidade": 1.63,
        "razao_dependencia_jovens": 31.98,
        "razao_dependencia_idosos": 12.44,
        "razao_dependencia": 44.42,
        "indice_envelhecimento": 38.92
    },
    {
        "ano": 2022,
        "populacao_total": 9272899,
        "homens": 4523622,
        "mulheres": 4749277,
        "nascimentos": 124291,
        "obitos": 62734,
        "taxa_crescimento_geometrico": 0.5,
        "taxa_bruta_natalidade": 13.4,
        "taxa_bruga_mortalidade": 6.77,
        "esperanca_vida_nascer": 75.07,
        "esperanca_vida_nascer_homens": 71.15,
        "esperanca_vida_nascer_mulheres": 79.02,
        "taxa_mortalidade_infantil": 11.56,
        "taxa_mortalidade_infantil_homens": 12.36,
        "taxa_mortalidade_infantil_mulheres": 10.72,
        "taxa_fecundidade": 1.61,
        "razao_dependencia_jovens": 31.26,
        "razao_dependencia_idosos": 12.73,
        "razao_dependencia": 44.0,
        "indice_envelhecimento": 40.73
    },
    {
        "ano": 2023,
        "populacao_total": 9317120,
        "homens": 4542512,
        "mulheres": 4774608,
        "nascimentos": 122903,
        "obitos": 63670,
        "taxa_crescimento_geometrico": 0.48,
        "taxa_bruta_natalidade": 13.19,
        "taxa_bruga_mortalidade": 6.83,
        "esperanca_vida_nascer": 75.25,
        "esperanca_vida_nascer_homens": 71.34,
        "esperanca_vida_nascer_mulheres": 79.19,
        "taxa_mortalidade_infantil": 11.24,
        "taxa_mortalidade_infantil_homens": 12.01,
        "taxa_mortalidade_infantil_mulheres": 10.43,
        "taxa_fecundidade": 1.6,
        "razao_dependencia_jovens": 30.61,
        "razao_dependencia_idosos": 13.05,
        "razao_dependencia": 43.66,
        "indice_envelhecimento": 42.63
    },
    {
        "ano": 2024,
        "populacao_total": 9359246,
        "homens": 4560381,
        "mulheres": 4798865,
        "nascimentos": 121533,
        "obitos": 64647,
        "taxa_crescimento_geometrico": 0.45,
        "taxa_bruta_natalidade": 12.99,
        "taxa_bruga_mortalidade": 6.91,
        "esperanca_vida_nascer": 75.43,
        "esperanca_vida_nascer_homens": 71.52,
        "esperanca_vida_nascer_mulheres": 79.35,
        "taxa_mortalidade_infantil": 10.95,
        "taxa_mortalidade_infantil_homens": 11.7,
        "taxa_mortalidade_infantil_mulheres": 10.17,
        "taxa_fecundidade": 1.59,
        "razao_dependencia_jovens": 30.01,
        "razao_dependencia_idosos": 13.41,
        "razao_dependencia": 43.42,
        "indice_envelhecimento": 44.68
    },
    {
        "ano": 2025,
        "populacao_total": 9399260,
        "homens": 4577225,
        "mulheres": 4822035,
        "nascimentos": 120192,
        "obitos": 65700,
        "taxa_crescimento_geometrico": 0.43,
        "taxa_bruta_natalidade": 12.79,
        "taxa_bruga_mortalidade": 6.99,
        "esperanca_vida_nascer": 75.6,
        "esperanca_vida_nascer_homens": 71.7,
        "esperanca_vida_nascer_mulheres": 79.51,
        "taxa_mortalidade_infantil": 10.7,
        "taxa_mortalidade_infantil_homens": 11.42,
        "taxa_mortalidade_infantil_mulheres": 9.94,
        "taxa_fecundidade": 1.58,
        "razao_dependencia_jovens": 29.47,
        "razao_dependencia_idosos": 13.82,
        "razao_dependencia": 43.29,
        "indice_envelhecimento": 46.9
    },
    {
        "ano": 2026,
        "populacao_total": 9437126,
        "homens": 4593041,
        "mulheres": 4844085,
        "nascimentos": 118868,
        "obitos": 66792,
        "taxa_crescimento_geometrico": 0.4,
        "taxa_bruta_natalidade": 12.6,
        "taxa_bruga_mortalidade": 7.08,
        "esperanca_vida_nascer": 75.76,
        "esperanca_vida_nascer_homens": 71.88,
        "esperanca_vida_nascer_mulheres": 79.66,
        "taxa_mortalidade_infantil": 10.47,
        "taxa_mortalidade_infantil_homens": 11.17,
        "taxa_mortalidade_infantil_mulheres": 9.74,
        "taxa_fecundidade": 1.57,
        "razao_dependencia_jovens": 28.97,
        "razao_dependencia_idosos": 14.28,
        "razao_dependencia": 43.26,
        "indice_envelhecimento": 49.3
    },
    {
        "ano": 2027,
        "populacao_total": 9472791,
        "homens": 4607808,
        "mulheres": 4864983,
        "nascimentos": 117524,
        "obitos": 67951,
        "taxa_crescimento_geometrico": 0.38,
        "taxa_bruta_natalidade": 12.41,
        "taxa_bruga_mortalidade": 7.17,
        "esperanca_vida_nascer": 75.92,
        "esperanca_vida_nascer_homens": 72.05,
        "esperanca_vida_nascer_mulheres": 79.81,
        "taxa_mortalidade_infantil": 10.26,
        "taxa_mortalidade_infantil_homens": 10.95,
        "taxa_mortalidade_infantil_mulheres": 9.55,
        "taxa_fecundidade": 1.57,
        "razao_dependencia_jovens": 28.53,
        "razao_dependencia_idosos": 14.8,
        "razao_dependencia": 43.33,
        "indice_envelhecimento": 51.87
    },
    {
        "ano": 2028,
        "populacao_total": 9506193,
        "homens": 4621493,
        "mulheres": 4884700,
        "nascimentos": 116169,
        "obitos": 69142,
        "taxa_crescimento_geometrico": 0.35,
        "taxa_bruta_natalidade": 12.22,
        "taxa_bruga_mortalidade": 7.27,
        "esperanca_vida_nascer": 76.08,
        "esperanca_vida_nascer_homens": 72.22,
        "esperanca_vida_nascer_mulheres": 79.95,
        "taxa_mortalidade_infantil": 10.08,
        "taxa_mortalidade_infantil_homens": 10.75,
        "taxa_mortalidade_infantil_mulheres": 9.38,
        "taxa_fecundidade": 1.56,
        "razao_dependencia_jovens": 28.12,
        "razao_dependencia_idosos": 15.35,
        "razao_dependencia": 43.47,
        "indice_envelhecimento": 54.59
    },
    {
        "ano": 2029,
        "populacao_total": 9537296,
        "homens": 4634089,
        "mulheres": 4903207,
        "nascimentos": 114821,
        "obitos": 70365,
        "taxa_crescimento_geometrico": 0.33,
        "taxa_bruta_natalidade": 12.04,
        "taxa_bruga_mortalidade": 7.38,
        "esperanca_vida_nascer": 76.23,
        "esperanca_vida_nascer_homens": 72.38,
        "esperanca_vida_nascer_mulheres": 80.08,
        "taxa_mortalidade_infantil": 9.92,
        "taxa_mortalidade_infantil_homens": 10.57,
        "taxa_mortalidade_infantil_mulheres": 9.23,
        "taxa_fecundidade": 1.56,
        "razao_dependencia_jovens": 27.74,
        "razao_dependencia_idosos": 15.92,
        "razao_dependencia": 43.66,
        "indice_envelhecimento": 57.39
    },
    {
        "ano": 2030,
        "populacao_total": 9566063,
        "homens": 4645561,
        "mulheres": 4920502,
        "nascimentos": 113487,
        "obitos": 71632,
        "taxa_crescimento_geometrico": 0.3,
        "taxa_bruta_natalidade": 11.86,
        "taxa_bruga_mortalidade": 7.49,
        "esperanca_vida_nascer": 76.37,
        "esperanca_vida_nascer_homens": 72.54,
        "esperanca_vida_nascer_mulheres": 80.21,
        "taxa_mortalidade_infantil": 9.77,
        "taxa_mortalidade_infantil_homens": 10.42,
        "taxa_mortalidade_infantil_mulheres": 9.1,
        "taxa_fecundidade": 1.55,
        "razao_dependencia_jovens": 27.38,
        "razao_dependencia_idosos": 16.49,
        "razao_dependencia": 43.87,
        "indice_envelhecimento": 60.22
    }
]