[
    {
        "ano": 2000,
        "populacao_total": 3472839,
        "homens": 1692945,
        "mulheres": 1779894,
        "nascimentos": 75858,
        "obitos": 30678,
        "taxa_crescimento_geometrico": null,
        "taxa_bruta_natalidade": 21.84,
        "taxa_bruga_mortalidade": 8.83,
        "esperanca_vida_nascer": 67.06,
        "esperanca_vida_nascer_homens": 63.5,
        "esperanca_vida_nascer_mulheres": 70.67,
        "taxa_mortalidade_infantil": 48.62,
        "taxa_mortalidade_infantil_homens": 55.9,
        "taxa_mortalidade_infantil_mulheres": 41.0,
        "taxa_fecundidade": 2.53,
        "razao_dependencia_jovens": 51.77,
        "razao_dependencia_idosos": 11.34,
        "razao_dependencia": 63.11,
        "indice_envelhecimento": 21.9
    },
    {
        "ano": 2001,
        "populacao_total": 3507296,
        "homens": 1710014,
        "mulheres": 1797282,
        "nascimentos": 75239,
        "obitos": 30382,
        "taxa_crescimento_geometrico": 0.99,
        "taxa_bruta_natalidade": 21.45,
        "taxa_bruga_mortalidade": 8.66,
        "esperanca_vida_nascer": 67.52,
        "esperanca_vida_nascer_homens": 63.93,
        "esperanca_vida_nascer_mulheres": 71.17,
        "taxa_mortalidade_infantil": 44.54,
        "taxa_mortalidade_infantil_homens": 49.97,
        "taxa_mortalidade_infantil_mulheres": 38.82,
        "taxa_fecundidade": 2.46,
        "razao_dependencia_jovens": 50.15,
        "razao_dependencia_idosos": 11.19,
        "razao_dependencia": 61.35,
        "indice_envelhecimento": 22.32
    },
    {
        "ano": 2002,
        "populacao_total": 3542012,
        "homens": 1727011,
        "mulheres": 1815001,
        "nascimentos": 74569,
        "obitos": 30005,
        "taxa_crescimento_geometrico": 0.99,
        "taxa_bruta_natalidade": 21.05,
        "taxa_bruga_mortalidade": 8.47,
        "esperanca_vida_nascer": 67.98,
        "esperanca_vida_nascer_homens": 64.34,
        "esperanca_vida_nascer_mulheres": 71.66,
        "taxa_mortalidade_infantil": 40.91,
        "taxa_mortalidade_infantil_homens": 44.92,
        "taxa_mortalidade_infantil_mulheres": 36.67,
        "taxa_fecundidade": 2.4,
        "razao_dependencia_jovens": 48.69,
        "razao_dependencia_idosos": 11.12,
        "razao_dependencia": 59.81,
        "indice_envelhecimento": 22.84
    },
    {
        "ano": 2003,
        "populacao_total": 3576975,
        "homens": 1743964,
        "mulheres": 1833011,
        "nascimentos": 73821,
        "obitos": 29653,
        "taxa_crescimento_geometrico": 0.99,
        "taxa_bruta_natalidade": 20.64,
        "taxa_bruga_mortalidade": 8.29,
        "esperanca_vida_nascer": 68.42,
        "esperanca_vida_nascer_homens": 64.75,
        "esperanca_vida_nascer_mulheres": 72.14,
        "taxa_mortalidade_infantil": 37.7,
        "taxa_mortalidade_infantil_homens": 40.65,
        "taxa_mortalidade_infantil_mulheres": 34.59,
        "taxa_fecundidade": 2.33,
        "razao_dependencia_jovens": 47.36,
        "razao_dependencia_idosos": 11.1,
        "razao_dependencia": 58.46,
        "indice_envelhecimento": 23.44
    },
    {
        "ano": 2004,
        "populacao_total": 3612078,
        "homens": 1760828,
        "mulheres": 1851250,
        "nascimentos": 72959,
        "obitos": 29338,
        "taxa_crescimento_geometrico": 0.98,
        "taxa_bruta_natalidade": 20.2,
        "taxa_bruga_mortalidade": 8.12,
        "esperanca_vida_nascer": 68.85,
        "esperanca_vida_nascer_homens": 65.14,
        "esperanca_vida_nascer_mulheres": 72.6,
        "taxa_mortalidade_infantil": 34.86,
        "taxa_mortalidade_infantil_homens": 37.02,
        "taxa_mortalidade_infantil_mulheres": 32.57,
        "taxa_fecundidade": 2.27,
        "razao_dependencia_jovens": 46.18,
        "razao_dependencia_idosos": 11.1,
        "razao_dependencia": 57.27,
        "indice_envelhecimento": 24.03
    },
    {
        "ano": 2005,
        "populacao_total": 3647204,
        "homens": 1777555,
        "mulheres": 1869649,
        "nascimentos": 71972,
        "obitos": 29035,
        "taxa_crescimento_geometrico": 0.97,
        "taxa_bruta_natalidade": 19.73,
        "taxa_bruga_mortalidade": 7.96,
        "esperanca_vida_nascer": 69.27,
        "esperanca_vida_nascer_homens": 65.53,
        "esperanca_vida_nascer_mulheres": 73.05,
        "taxa_mortalidade_infantil": 32.31,
        "taxa_mortalidade_infantil_homens": 33.91,
        "taxa_mortalidade_infantil_mulheres": 30.64,
        "taxa_fecundidade": 2.21,
        "razao_dependencia_jovens": 45.11,
        "razao_dependencia_idosos": 11.1,
        "razao_dependencia": 56.21,
        "indice_envelhecimento": 24.59
    },
    {
        "ano": 2006,
        "populacao_total": 3682222,
        "homens": 1794079,
        "mulheres": 1888143,
        "nascimentos": 70903,
        "obitos": 28774,
        "taxa_crescimento_geometrico": 0.96,
        "taxa_bruta_natalidade": 19.26,
        "taxa_bruga_mortalidade": 7.81,
        "esperanca_vida_nascer": 69.69,
        "esperanca_vida_nascer_homens": 65.92,
        "esperanca_vida_nascer_mulheres": 73.49,
        "taxa_mortalidade_infantil": 30.03,
        "taxa_mortalidade_infantil_homens": 31.21,
        "taxa_mortalidade_infantil_mulheres": 28.79,
        "taxa_fecundidade": 2.16,
        "razao_dependencia_jovens": 44.16,
        "razao_dependencia_idosos": 11.1,
        "razao_dependencia": 55.25,
        "indice_envelhecimento": 25.13
    },
    {
        "ano": 2007,
        "populacao_total": 3717022,
        "homens": 1810353,
        "mulheres": 1906669,
        "nascimentos": 69786,
        "obitos": 28573,
        "taxa_crescimento_geometrico": 0.95,
        "taxa_bruta_natalidade": 18.77,
        "taxa_bruga_mortalidade": 7.69,
        "esperanca_vida_nascer": 70.09,
        "esperanca_vida_nascer_homens": 66.29,
        "esperanca_vida_nascer_mulheres": 73.91,
        "taxa_mortalidade_infantil": 27.97,
        "taxa_mortalidade_infantil_homens": 28.86,
        "taxa_mortalidade_infantil_mulheres": 27.04,
        "taxa_fecundidade": 2.11,
        "razao_dependencia_jovens": 43.29,
        "razao_dependencia_idosos": 11.1,
        "razao_dependencia": 54.39,
        "indice_envelhecimento": 25.65
    },
    {
        "ano": 2008,
        "populacao_total": 3751507,
        "homens": 1826334,
        "mulheres": 1925173,
        "nascimentos": 68628,
        "obitos": 28411,
        "taxa_crescimento_geometrico": 0.93,
        "taxa_bruta_natalidade": 18.29,
        "taxa_bruga_mortalidade": 7.57,
        "esperanca_vida_nascer": 70.48,
        "esperanca_vida_nascer_homens": 66.66,
        "esperanca_vida_nascer_mulheres": 74.32,
        "taxa_mortalidade_infantil": 26.11,
        "taxa_mortalidade_infantil_homens": 26.78,
        "taxa_mortalidade_infantil_mulheres": 25.4,
        "taxa_fecundidade": 2.06,
        "razao_dependencia_jovens": 42.49,
        "razao_dependencia_idosos": 11.12,
        "razao_dependencia": 53.62,
        "indice_envelhecimento": 26.18
    },
    {
        "ano": 2009,
        "populacao_total": 3785598,
        "homens": 1841981,
        "mulheres": 1943617,
        "nascimentos": 67436,
        "obitos": 28292,
        "taxa_crescimento_geometrico": 0.91,
        "taxa_bruta_natalidade": 17.81,
        "taxa_bruga_mortalidade": 7.47,
        "esperanca_vida_nascer": 70.86,
        "esperanca_vida_nascer_homens": 67.03,
        "esperanca_vida_nascer_mulheres": 74.71,
        "taxa_mortalidade_infantil": 24.41,
        "taxa_mortalidade_infantil_homens": 24.93,
        "taxa_mortalidade_infantil_mulheres": 23.86,
        "taxa_fecundidade": 2.01,
        "razao_dependencia_jovens": 41.78,
        "razao_dependencia_idosos": 11.18,
        "razao_dependencia": 52.96,
        "indice_envelhecimento": 26.76
    },
    {
        "ano": 2010,
        "populacao_total": 3819237,
        "homens": 1857265,
        "mulheres": 1961972,
        "nascimentos": 66217,
        "obitos": 28196,
        "taxa_crescimento_geometrico": 0.89,
        "taxa_bruta_natalidade": 17.34,
        "taxa_bruga_mortalidade": 7.38,
        "esperanca_vida_nascer": 71.24,
        "esperanca_vida_nascer_homens": 67.38,
        "esperanca_vida_nascer_mulheres": 75.1,
        "taxa_mortalidade_infantil": 22.87,
        "taxa_mortalidade_infantil_homens": 23.29,
        "taxa_mortalidade_infantil_mulheres": 22.43,
        "taxa_fecundidade": 1.97,
        "razao_dependencia_jovens": 41.12,
        "razao_dependencia_idosos": 11.28,
        "razao_dependencia": 52.4,
        "indice_envelhecimento": 27.43
    },
    {
        "ano": 2011,
        "populacao_total": 3852082,
        "homens": 1872075,
        "mulheres": 1980007,
        "nascimentos": 64985,
        "obitos": 28145,
        "taxa_crescimento_geometrico": 0.86,
        "taxa_bruta_natalidade": 16.87,
        "taxa_bruga_mortalidade": 7.31,
        "esperanca_vida_nascer": 71.59,
        "esperanca_vida_nascer_homens": 67.73,
        "esperanca_vida_nascer_mulheres": 75.46,
        "taxa_mortalidade_infantil": 21.46,
        "taxa_mortalidade_infantil_homens": 21.81,
        "taxa_mortalidade_infantil_mulheres": 21.1,
        "taxa_fecundidade": 1.93,
        "razao_dependencia_jovens": 40.49,
        "razao_dependencia_idosos": 11.42,
        "razao_dependencia": 51.91,
        "indice_envelhecimento": 28.19
    },
    {
        "ano": 2012,
        "populacao_total": 3883822,
        "homens": 1886324,
        "mulheres": 1997498,
        "nascimentos": 63756,
        "obitos": 28129,
        "taxa_crescimento_geometrico": 0.82,
        "taxa_bruta_natalidade": 16.42,
        "taxa_bruga_mortalidade": 7.24,
        "esperanca_vida_nascer": 71.94,
        "esperanca_vida_nascer_homens": 68.06,
        "esperanca_vida_nascer_mulheres": 75.82,
        "taxa_mortalidade_infantil": 20.18,
        "taxa_mortalidade_infantil_homens": 20.47,
        "taxa_mortalidade_infantil_mulheres": 19.87,
        "taxa_fecundidade": 1.89,
        "razao_dependencia_jovens": 39.87,
        "razao_dependencia_idosos": 11.59,
        "razao_dependencia": 51.46,
        "indice_envelhecimento": 29.06
    },
    {
        "ano": 2013,
        "populacao_total": 3914421,
        "homens": 1899995,
        "mulheres": 2014426,
        "nascimentos": 62547,
        "obitos": 28139,
        "taxa_crescimento_geometrico": 0.79,
        "taxa_bruta_natalidade": 15.98,
        "taxa_bruga_mortalidade": 7.19,
        "esperanca_vida_nascer": 72.29,
        "esperanca_vida_nascer_homens": 68.4,
        "esperanca_vida_nascer_mulheres": 76.16,
        "taxa_mortalidade_infantil": 19.02,
        "taxa_mortalidade_infantil_homens": 19.27,
        "taxa_mortalidade_infantil_mulheres": 18.75,
        "taxa_fecundidade": 1.85,
        "razao_dependencia_jovens": 39.24,
        "razao_dependencia_idosos": 11.78,
        "razao_dependencia": 51.02,
        "indice_envelhecimento": 30.03
    },
    {
        "ano": 2014,
        "populacao_total": 3943885,
        "homens": 1913103,
        "mulheres": 2030782,
        "nascimentos": 61374,
        "obitos": 28188,
        "taxa_crescimento_geometrico": 0.75,
        "taxa_bruta_natalidade": 15.56,
        "taxa_bruga_mortalidade": 7.15,
        "esperanca_vida_nascer": 72.61,
        "esperanca_vida_nascer_homens": 68.72,
        "esperanca_vida_nascer_mulheres": 76.49,
        "taxa_mortalidade_infantil": 17.97,
        "taxa_mortalidade_infantil_homens": 18.19,
        "taxa_mortalidade_infantil_mulheres": 17.72,
        "taxa_fecundidade": 1.82,
        "razao_dependencia_jovens": 38.57,
        "razao_dependencia_idosos": 11.99,
        "razao_dependencia": 50.56,
        "indice_envelhecimento": 31.07
    },
    {
        "ano": 2015,
        "populacao_total": 3972202,
        "homens": 1925643,
        "mulheres": 2046559,
        "nascimentos": 60247,
        "obitos": 28258,
        "taxa_crescimento_geometrico": 0.72,
        "taxa_bruta_natalidade": 15.17,
        "taxa_bruga_mortalidade": 7.11,
        "esperanca_vida_nascer": 72.93,
        "esperanca_vida_nascer_homens": 69.03,
        "esperanca_vida_nascer_mulheres": 76.8,
        "taxa_mortalidade_infantil": 17.01,
        "taxa_mortalidade_infantil_homens": 17.22,
        "taxa_mortalidade_infantil_mulheres": 16.79,
        "taxa_fecundidade": 1.79,
        "razao_dependencia_jovens": 37.86,
        "razao_dependencia_idosos": 12.18,
        "razao_dependencia": 50.05,
        "indice_envelhecimento": 32.18
    },
    {
        "ano": 2016,
        "populacao_total": 3999415,
        "homens": 1937644,
        "mulheres": 2061771,
        "nascimentos": 59238,
        "obitos": 28370,
        "taxa_crescimento_geometrico": 0.69,
        "taxa_bruta_natalidade": 14.81,
        "taxa_bruga_mortalidade": 7.09,
        "esperanca_vida_nascer": 73.23,
        "esperanca_vida_nascer_homens": 69.34,
        "esperanca_vida_nascer_mulheres": 77.11,
        "taxa_mortalidade_infantil": 16.15,
        "taxa_mortalidade_infantil_homens": 16.34,
        "taxa_mortalidade_infantil_mulheres": 15.94,
        "taxa_fecundidade": 1.76,
        "razao_dependencia_jovens": 37.0,
        "razao_dependencia_idosos": 12.37,
        "razao_dependencia": 49.38,
        "indice_envelhecimento": 33.44
    },
    {
        "ano": 2017,
        "populacao_total": 4025558,
        "homens": 1949130,
        "mulheres": 2076428,
        "nascimentos": 58293,
        "obitos": 28512,
        "taxa_crescimento_geometrico": 0.65,
        "taxa_bruta_natalidade": 14.48,
        "taxa_bruga_mortalidade": 7.08,
        "esperanca_vida_nascer": 73.53,
        "esperanca_vida_nascer_homens": 69.63,
        "esperanca_vida_nascer_mulheres": 77.4,
        "taxa_mortalidade_infantil": 15.37,
        "taxa_mortalidade_infantil_homens": 15.56,
        "taxa_mortalidade_infantil_mulheres": 15.17,
        "taxa_fecundidade": 1.74,
        "razao_dependencia_jovens": 36.14,
        "razao_dependencia_idosos": 12.57,
        "razao_dependencia": 48.7,
        "indice_envelhecimento": 34.78
    },
    {
        "ano": 2018,
        "populacao_total": 4050662,
        "homens": 1960114,
        "mulheres": 2090548,
        "nascimentos": 57405,
        "obitos": 28683,
        "taxa_crescimento_geometrico": 0.62,
        "taxa_bruta_natalidade": 14.17,
        "taxa_bruga_mortalidade": 7.08,
        "esperanca_vida_nascer": 73.82,
        "esperanca_vida_nascer_homens": 69.92,
        "esperanca_vida_nascer_mulheres": 77.67,
        "taxa_mortalidade_infantil": 14.66,
        "taxa_mortalidade_infantil_homens": 14.85,
        "taxa_mortalidade_infantil_mulheres": 14.47,
        "taxa_fecundidade": 1.71,
        "razao_dependencia_jovens": 35.27,
        "razao_dependencia_idosos": 12.77,
        "razao_dependencia": 48.03,
        "indice_envelhecimento": 36.2
    },
    {
        "ano": 2019,
        "populacao_total": 4074755,
        "homens": 1970613,
        "mulheres": 2104142,
        "nascimentos": 56570,
        "obitos": 28888,
        "taxa_crescimento_geometrico": 0.59,
        "taxa_bruta_natalidade": 13.88,
        "taxa_bruga_mortalidade": 7.09,
        "esperanca_vida_nascer": 74.09,
        "esperanca_vida_nascer_homens": 70.2,
        "esperanca_vida_nascer_mulheres": 77.94,
        "taxa_mortalidade_infantil": 14.03,
        "taxa_mortalidade_infantil_homens": 14.21,
        "taxa_mortalidade_infantil_mulheres": 13.85,
        "taxa_fecundidade": 1.69,
        "razao_dependencia_jovens": 34.4,
        "razao_dependencia_idosos": 12.98,
        "razao_dependencia": 47.38,
        "indice_envelhecimento": 37.72
    },
    {
        "ano": 2020,
        "populacao_total": 4097859,
        "homens": 1980643,
        "mulheres": 2117216,
        "nascimentos": 55777,
        "obitos": 29106,
        "taxa_crescimento_geometrico": 0.57,
        "taxa_bruta_natalidade": 13.61,
        "taxa_bruga_mortalidade": 7.1,
        "esperanca_vida_nascer": 74.36,
        "esperanca_vida_nascer_homens": 70.47,
        "esperanca_vida_nascer_mulheres": 78.19,
        "taxa_mortalidade_infantil": 13.47,
        "taxa_mortalidade_infantil_homens": 13.64,
        "taxa_mortalidade_infantil_mulheres": 13.28,
        "taxa_fecundidade": 1.67,
        "razao_dependencia_jovens": 33.56,
        "razao_dependencia_idosos": 13.21,
        "razao_dependencia": 46.77,
        "indice_envelhecimento": 39.35
    },
    {
        "ano": 2021,
        "populacao_total": 4119993,
        "homens": 1990213,
        "mulheres": 2129780,
        "nascimentos": 55035,
        "obitos": 29352,
        "taxa_crescimento_geometrico": 0.54,
        "taxa_bruta_natalidade": 13.36,
        "taxa_bruga_mortalidade": 7.12,
        "esperanca_vida_nascer": 74.62,
        "esperanca_vida_nascer_homens": 70.73,
        "esperanca_vida_nascer_mulheres": 78.44,
        "taxa_mortalidade_infantil": 12.96,
        "taxa_mortalidade_infantil_homens": 13.13,
        "taxa_mortalidade_infantil_mulheres": 12.78,
        "taxa_fecundidade": 1.66,
        "razao_dependencia_jovens": 32.75,
        "razao_dependencia_idosos": 13.45,
        "razao_dependencia": 46.2,
        "indice_envelhecimento": 41.07
    },
    {
        "ano": 2022,
        "populacao_total": 4141161,
        "homens": 1999318,
        "mulheres": 2141843,
        "nascimentos": 54295,
        "obitos": 29631,
        "taxa_crescimento_geometrico": 0.51,
        "taxa_bruta_natalidade": 13.11,
        "taxa_bruga_mortalidade": 7.16,
        "esperanca_vida_nascer": 74.86,
        "esperanca_vida_nascer_homens": 70.99,
        "esperanca_vida_nascer_mulheres": 78.67,
        "taxa_mortalidade_infantil": 12.51,
        "taxa_mortalidade_infantil_homens": 12.68,
        "taxa_mortalidade_infantil_mulheres": 12.33,
        "taxa_fecundidade": 1.64,
        "razao_dependencia_jovens": 31.96,
        "razao_dependencia_idosos": 13.71,
        "razao_dependencia": 45.67,
        "indice_envelhecimento": 42.9
    },
    {
        "ano": 2023,
        "populacao_total": 4161337,
        "homens": 2007948,
        "mulheres": 2153389,
        "nascimentos": 53564,
        "obitos": 29944,
        "taxa_crescimento_geometrico": 0.49,
        "taxa_bruta_natalidade": 12.87,
        "taxa_bruga_mortalidade": 7.2,
        "esperanca_vida_nascer": 75.09,
        "esperanca_vida_nascer_homens": 71.24,
        "esperanca_vida_nascer_mulheres": 78.89,
        "taxa_mortalidade_infantil": 12.1,
        "taxa_mortalidade_infantil_homens": 12.27,
        "taxa_mortalidade_infantil_mulheres": 11.92,
        "taxa_fecundidade": 1.62,
        "razao_dependencia_jovens": 31.22,
        "razao_dependencia_idosos": 14.0,
        "razao_dependencia": 45.21,
        "indice_envelhecimento": 44.84
    },
    {
        "ano": 2024,
        "populacao_total": 4180508,
        "homens": 2016099,
        "mulheres": 2164409,
        "nascimentos": 52852,
        "obitos": 30288,
        "taxa_crescimento_geometrico": 0.46,
        "taxa_bruta_natalidade": 12.64,
        "taxa_bruga_mortalidade": 7.25,
        "esperanca_vida_nascer": 75.32,
        "esperanca_vida_nascer_homens": 71.47,
        "esperanca_vida_nascer_mulheres": 79.1,
        "taxa_mortalidade_infantil": 11.74,
        "taxa_mortalidade_infantil_homens": 11.91,
        "taxa_mortalidade_infantil_mulheres": 11.56,
        "taxa_fecundidade": 1.61,
        "razao_dependencia_jovens": 30.51,
        "razao_dependencia_idosos": 14.33,
        "razao_dependencia": 44.84,
        "indice_envelhecimento": 46.95
    },
    {
        "ano": 2025,
        "populacao_total": 4198671,
        "homens": 2023774,
        "mulheres": 2174897,
        "nascimentos": 52168,
        "obitos": 30668,
        "taxa_crescimento_geometrico": 0.43,
        "taxa_bruta_natalidade": 12.42,
        "taxa_bruga_mortalidade": 7.3,
        "esperanca_vida_nascer": 75.54,
        "esperanca_vida_nascer_homens": 71.7,
        "esperanca_vida_nascer_mulheres": 79.31,
        "taxa_mortalidade_infantil": 11.41,
        "taxa_mortalidade_infantil_homens": 11.59,
        "taxa_mortalidade_infantil_mulheres": 11.24,
        "taxa_fecundidade": 1.6,
        "razao_dependencia_jovens": 29.86,
        "razao_dependencia_idosos": 14.7,
        "razao_dependencia": 44.56,
        "indice_envelhecimento": 49.24
    },
    {
        "ano": 2026,
        "populacao_total": 4215840,
        "homens": 2030981,
        "mulheres": 2184859,
        "nascimentos": 51519,
        "obitos": 31085,
        "taxa_crescimento_geometrico": 0.41,
        "taxa_bruta_natalidade": 12.22,
        "taxa_bruga_mortalidade": 7.37,
        "esperanca_vida_nascer": 75.75,
        "esperanca_vida_nascer_homens": 71.93,
        "esperanca_vida_nascer_mulheres": 79.5,
        "taxa_mortalidade_infantil": 11.13,
        "taxa_mortalidade_infantil_homens": 11.3,
        "taxa_mortalidade_infantil_mulheres": 10.95,
        "taxa_fecundidade": 1.58,
        "razao_dependencia_jovens": 29.25,
        "razao_dependencia_idosos": 15.13,
        "razao_dependencia": 44.38,
        "indice_envelhecimento": 51.71
    },
    {
        "ano": 2027,
        "populacao_total": 4232008,
        "homens": 2037709,
        "mulheres": 2194299,
        "nascimentos": 50885,
        "obitos": 31535,
        "taxa_crescimento_geometrico": 0.38,
        "taxa_bruta_natalidade": 12.02,
        "taxa_bruga_mortalidade": 7.45,
        "esperanca_vida_nascer": 75.95,
        "esperanca_vida_nascer_homens": 72.14,
        "esperanca_vida_nascer_mulheres": 79.68,
        "taxa_mortalidade_infantil": 10.87,
        "taxa_mortalidade_infantil_homens": 11.04,
        "taxa_mortalidade_infantil_mulheres": 10.7,
        "taxa_fecundidade": 1.57,
        "razao_dependencia_jovens": 28.7,
        "razao_dependencia_idosos": 15.6,
        "razao_dependencia": 44.3,
        "indice_envelhecimento": 54.37
    },
    {
        "ano": 2028,
        "populacao_total": 4247157,
        "homens": 2043958,
        "mulheres": 2203199,
        "nascimentos": 50273,
        "obitos": 32011,
        "taxa_crescimento_geometrico": 0.36,
        "taxa_bruta_natalidade": 11.84,
        "taxa_bruga_mortalidade": 7.54,
        "esperanca_vida_nascer": 76.15,
        "esperanca_vida_nascer_homens": 72.35,
        "esperanca_vida_nascer_mulheres": 79.86,
        "taxa_mortalidade_infantil": 10.64,
        "taxa_mortalidade_infantil_homens": 10.81,
        "taxa_mortalidade_infantil_mulheres": 10.47,
        "taxa_fecundidade": 1.56,
        "razao_dependencia_jovens": 28.19,
        "razao_dependencia_idosos": 16.12,
        "razao_dependencia": 44.31,
        "indice_envelhecimento": 57.17
    },
    {
        "ano": 2029,
        "populacao_total": 4261314,
        "homens": 2049744,
        "mulheres": 2211570,
        "nascimentos": 49693,
        "obitos": 32501,
        "taxa_crescimento_geometrico": 0.33,
        "taxa_bruta_natalidade": 11.66,
        "taxa_bruga_mortalidade": 7.63,
        "esperanca_vida_nascer": 76.33,
        "esperanca_vida_nascer_homens": 72.55,
        "esperanca_vida_nascer_mulheres": 80.03,
        "taxa_mortalidade_infantil": 10.45,
        "taxa_mortalidade_infantil_homens": 10.61,
        "taxa_mortalidade_infantil_mulheres": 10.27,
        "taxa_fecundidade": 1.56,
        "razao_dependencia_jovens": 27.72,
        "razao_dependencia_idosos": 16.65,
        "razao_dependencia": 44.37,
        "indice_envelhecimento": 60.07
    },
    {
        "ano": 2030,
        "populacao_total": 4274504,
        "homens": 2055073,
        "mulheres": 2219431,
        "nascimentos": 49149,
        "obitos": 33004,
        "taxa_crescimento_geometrico": 0.31,
        "taxa_bruta_natalidade": 11.5,
        "taxa_bruga_mortalidade": 7.72,
        "esperanca_vida_nascer": 76.51,
        "esperanca_vida_nascer_homens": 72.74,
        "esperanca_vida_nascer_mulheres": 80.18,
        "taxa_mortalidade_infantil": 10.27,
        "taxa_mortalidade_infantil_homens": 10.43,
        "taxa_mortalidade_infantil_mulheres": 10.09,
        "taxa_fecundidade": 1.55,
        "razao_dependencia_jovens": 27.29,
        "razao_dependencia_idosos": 17.2,
        "razao_dependencia": 44.48,
        "indice_envelhecimento": 63.03
    }
]